calc_demo_pi/__init__.py
calc_demo_pi/calc_demo.py
calc_demo_pi/Chebychev/__init__.py
calc_demo_pi/Chebychev/func.py
calc_demo_pi-0.0.5.dist-info/LICENSE
calc_demo_pi-0.0.5.dist-info/METADATA
calc_demo_pi-0.0.5.dist-info/WHEEL
calc_demo_pi-0.0.5.dist-info/top_level.txt
calc_demo_pi-0.0.5.dist-info/RECORD
