Metadata-Version: 2.1
Name: calc-demo-pi
Version: 0.0.5
Summary: Breve descripción
Home-page: https://gitlab/publish
Author: mfermin
Author-email: email@ib.edu.ar
License: UNKNOWN
Platform: UNKNOWN
Classifier: Programming Language :: Python :: 3
Classifier: Operating System :: OS Independent
Classifier: License :: OSI Approved :: MIT License
License-File: LICENSE
